vision_stuff/__init__.py
vision_stuff/vision_stuff.py
vision_stuff-0.1.3.dist-info/LICENSE.txt
vision_stuff-0.1.3.dist-info/METADATA
vision_stuff-0.1.3.dist-info/WHEEL
vision_stuff-0.1.3.dist-info/top_level.txt
vision_stuff-0.1.3.dist-info/RECORD
