Metadata-Version: 2.1
Name: vision-stuff
Version: 0.1.3
Summary: tools for image conversion
Home-page: https://github.com/streanger/vision_stuff
Author: streanger
Author-email: divisionexe@gmail.com
License: MIT
Keywords: vision image machine tools
Platform: UNKNOWN
Classifier: Programming Language :: Python :: 3
Classifier: License :: OSI Approved :: MIT License
Classifier: Operating System :: OS Independent
Requires-Dist: numpy
Requires-Dist: opencv-python
